cge/__init__.py
cge/_exceptions.py
cge/_partial.py
cge/_screenclear.py
cge/colors.py
cge/ext/__init__.py
cge/ext/legacy/func.py
cge/ext/legacy/text.py
cgepy-0.7.5.dist-info/LICENSE.md
cgepy-0.7.5.dist-info/METADATA
cgepy-0.7.5.dist-info/WHEEL
cgepy-0.7.5.dist-info/RECORD
