Metadata-Version: 2.1
Name: cgePy
Version: 0.7.5
Summary: A lightweight terminal graphics engine
Home-page: https://github.com/catbox305/cge
License: MIT
Author: catbox305
Requires-Python: >=3.7,<4.0
Classifier: License :: OSI Approved :: MIT License
Classifier: Programming Language :: Python :: 3
Classifier: Programming Language :: Python :: 3.7
Classifier: Programming Language :: Python :: 3.8
Classifier: Programming Language :: Python :: 3.9
Classifier: Programming Language :: Python :: 3.10
Classifier: Programming Language :: Python :: 3.11
Classifier: Programming Language :: Python :: 3.12
Project-URL: Documentation, https://cgepy.github.io/docs
Project-URL: Repository, https://github.com/catbox305/cge
